[
  {
    "code": "%",
    "name": "所有類別"
  },
  {
    "code": "a2",
    "name": "共同必修"
  },
  {
    "code": "b1",
    "name": "系定必修"
  },
  {
    "code": "b2",
    "name": "系定必修 (學科)"
  },
  {
    "code": "b4",
    "name": "系定選修"
  },
  {
    "code": "b5",
    "name": "系定選修 (學科)"
  },
  {
    "code": "b6",
    "name": "系定選修 (術科)"
  },
  {
    "code": "b7",
    "name": "專長 (水陸球技藝)"
  },
  {
    "code": "Bc",
    "name": "共同選修"
  },
  {
    "code": "BN",
    "name": "藝術與美感領域"
  },
  {
    "code": "BO",
    "name": "人文與文化思考領域"
  },
  {
    "code": "BP",
    "name": "公民素養與社會探索領域"
  },
  {
    "code": "BQ",
    "name": "自然、生命與科技領域"
  },
  {
    "code": "BV",
    "name": "通識其它"
  },
  {
    "code": "j3",
    "name": "教育方法課程"
  },
  {
    "code": "k6",
    "name": "教保專業知能課程"
  }
]
